_jpype.cp39-win_amd64.pyd
org.jpype.jar
jpype/__init__.py
jpype/_classpath.py
jpype/_core.py
jpype/_gui.py
jpype/_jarray.py
jpype/_jarray.pyi
jpype/_jclass.py
jpype/_jcollection.py
jpype/_jcollection.pyi
jpype/_jcustomizer.py
jpype/_jexception.py
jpype/_jinit.py
jpype/_jio.py
jpype/_jio.pyi
jpype/_jmethod.py
jpype/_jobject.py
jpype/_jpackage.py
jpype/_jproxy.py
jpype/_jstring.py
jpype/_jthread.py
jpype/_jvmfinder.py
jpype/_pykeywords.py
jpype/beans.py
jpype/config.py
jpype/dbapi2.py
jpype/imports.py
jpype/nio.py
jpype/pickle.py
jpype/protocol.py
jpype/types.py
jpype/_pyinstaller/entry_points.py
jpype/_pyinstaller/example.py
jpype/_pyinstaller/hook-jpype.py
jpype/_pyinstaller/test_jpype_pyinstaller.py
jpype1-1.6.0.dist-info/licenses/AUTHORS.rst
jpype1-1.6.0.dist-info/licenses/LICENSE
jpype1-1.6.0.dist-info/licenses/NOTICE
jpype1-1.6.0.dist-info/METADATA
jpype1-1.6.0.dist-info/WHEEL
jpype1-1.6.0.dist-info/entry_points.txt
jpype1-1.6.0.dist-info/top_level.txt
jpype1-1.6.0.dist-info/RECORD
